script/test.py
python_lib-0.1.0.dist-info/LICENSE
python_lib-0.1.0.dist-info/METADATA
python_lib-0.1.0.dist-info/WHEEL
python_lib-0.1.0.dist-info/top_level.txt
python_lib-0.1.0.dist-info/RECORD
