Metadata-Version: 2.1
Name: python-lib
Version: 0.1.0
Summary: My short description for my project.
Home-page: https://github.com/Jackybecomebetter/python_lib
Author: jacky_huang
Author-email: 1412165974@qq.com
License: MIT
Platform: UNKNOWN
Classifier: License :: OSI Approved :: MIT License
Classifier: Programming Language :: Python
Classifier: Programming Language :: Python :: 3
Classifier: Programming Language :: Python :: 3.6
Classifier: Programming Language :: Python :: Implementation :: CPython
Classifier: Programming Language :: Python :: Implementation :: PyPy
Requires-Python: >=3.6.0
